setup.py
probpackage/Binomialdistribution.py
probpackage/Gaussiandistribution.py
probpackage/Generaldistribution.py
probpackage/__init__.py
probpackage.egg-info/PKG-INFO
probpackage.egg-info/SOURCES.txt
probpackage.egg-info/dependency_links.txt
probpackage.egg-info/not-zip-safe
probpackage.egg-info/top_level.txt