Metadata-Version: 1.0
Name: probpackage
Version: 1.2
Summary: Gaussian and Binominal Distributions 
Home-page: UNKNOWN
Author: mohammed lokma
Author-email: UNKNOWN
License: UNKNOWN
Platform: UNKNOWN
